{
  "$schema": "../gen/schemas/desktop-schema.json",
  "identifier": "api-bridge",
  "description": "Permissions for the api-bridge plugin",
  "windows": ["main"],
  "permissions": [
    "api-bridge:default",
    "api-bridge:allow-load-surface-atlas",
    "api-bridge:allow-load-surface-overlay",
    "api-bridge:allow-remote-mount-connect",
    "api-bridge:allow-remote-mount-respond-host-key",
    "api-bridge:allow-remote-mount-respond-auth",
    "api-bridge:allow-remote-mount-unmount",
    "api-bridge:allow-list-remote-mount-profiles",
    "api-bridge:allow-remove-remote-mount-profile"
  ]
}
